setup.cfg
setup.py
pysitron/__init__.py
pysitron/icon.py
pysitron/syntax_helpers.py
pysitron.egg-info/PKG-INFO
pysitron.egg-info/SOURCES.txt
pysitron.egg-info/dependency_links.txt
pysitron.egg-info/requires.txt
pysitron.egg-info/top_level.txt