Metadata-Version: 1.1
Name: pysitron
Version: 0.0.5.dev5
Summary: A framework for building desktop applications in Python using web technologies
Home-page: https://github.com/jVinc/Pysitron
Author: Jackie Vincent Larsen
Author-email: jackie.v.larsen@gmail.com
License: UNKNOWN
Download-URL: https://github.com/jVinc/Pysitron/tree/v0.0.5.2
Keywords: app-development,desktop,web
Platform: UNKNOWN
Classifier: License :: OSI Approved :: MIT License
Classifier: Programming Language :: Python
Classifier: Programming Language :: Python :: 3
